djangoheads/__init__.py
djangoheads/apps.py
djangoheads/management/__init__.py
djangoheads/management/commands/__init__.py
djangoheads/management/commands/initdjango.py
djangoheads/management/commands/waiter.py
djangoheads/management/commands/waiter_checks/__init__.py
djangoheads/management/commands/waiter_checks/check__base.py
djangoheads/management/commands/waiter_checks/check_caches.py
djangoheads/management/commands/waiter_checks/check_celery.py
djangoheads/management/commands/waiter_checks/check_db_available.py
djangoheads/management/commands/waiter_checks/check_db_write.py
djangoheads/management/commands/waiter_checks/check_migrate.py
djangoheads-1.2.1.dist-info/LICENSE
djangoheads-1.2.1.dist-info/METADATA
djangoheads-1.2.1.dist-info/WHEEL
djangoheads-1.2.1.dist-info/RECORD
